DeepPhysX-22.12.1-py3.10-nspkg.pth
DeepPhysX/cli.py
DeepPhysX/Core/__init__.py
DeepPhysX/Core/AsyncSocket/AbstractEnvironment.py
DeepPhysX/Core/AsyncSocket/BytesConverter.py
DeepPhysX/Core/AsyncSocket/TcpIpClient.py
DeepPhysX/Core/AsyncSocket/TcpIpObject.py
DeepPhysX/Core/AsyncSocket/TcpIpServer.py
DeepPhysX/Core/AsyncSocket/__init__.py
DeepPhysX/Core/Database/BaseDatabaseConfig.py
DeepPhysX/Core/Database/DatabaseHandler.py
DeepPhysX/Core/Database/__init__.py
DeepPhysX/Core/Environment/BaseEnvironment.py
DeepPhysX/Core/Environment/BaseEnvironmentConfig.py
DeepPhysX/Core/Environment/__init__.py
DeepPhysX/Core/Environment/launcherBaseEnvironment.py
DeepPhysX/Core/Manager/DataManager.py
DeepPhysX/Core/Manager/DatabaseManager.py
DeepPhysX/Core/Manager/EnvironmentManager.py
DeepPhysX/Core/Manager/NetworkManager.py
DeepPhysX/Core/Manager/StatsManager.py
DeepPhysX/Core/Manager/__init__.py
DeepPhysX/Core/Network/BaseNetwork.py
DeepPhysX/Core/Network/BaseNetworkConfig.py
DeepPhysX/Core/Network/BaseOptimization.py
DeepPhysX/Core/Network/BaseTransformation.py
DeepPhysX/Core/Network/__init__.py
DeepPhysX/Core/Pipelines/BaseDataGeneration.py
DeepPhysX/Core/Pipelines/BasePipeline.py
DeepPhysX/Core/Pipelines/BasePrediction.py
DeepPhysX/Core/Pipelines/BaseTraining.py
DeepPhysX/Core/Pipelines/__init__.py
DeepPhysX/Core/Utils/__init__.py
DeepPhysX/Core/Utils/configs.py
DeepPhysX/Core/Utils/converter.py
DeepPhysX/Core/Utils/data_downloader.py
DeepPhysX/Core/Utils/jsonUtils.py
DeepPhysX/Core/Utils/mathUtils.py
DeepPhysX/Core/Utils/path.py
DeepPhysX/Core/Utils/tensor_transform_utils.py
DeepPhysX/Core/Utils/Visualizer/GridMapping.py
DeepPhysX/Core/Utils/Visualizer/SampleVisualizer.py
DeepPhysX/Core/Utils/Visualizer/__init__.py
DeepPhysX/Core/Utils/Visualizer/barycentric_mapping.py
DeepPhysX/examples/Core/demos/__init__.py
DeepPhysX/examples/Core/demos/Armadillo/__init__.py
DeepPhysX/examples/Core/demos/Armadillo/FC/__init__.py
DeepPhysX/examples/Core/demos/Armadillo/FC/download.py
DeepPhysX-22.12.1.dist-info/LICENSE
DeepPhysX-22.12.1.dist-info/METADATA
DeepPhysX-22.12.1.dist-info/WHEEL
DeepPhysX-22.12.1.dist-info/entry_points.txt
DeepPhysX-22.12.1.dist-info/namespace_packages.txt
DeepPhysX-22.12.1.dist-info/top_level.txt
DeepPhysX-22.12.1.dist-info/RECORD
