Metadata-Version: 2.1
Name: DeepPhysX
Version: 22.12.1
Summary: A Python framework interfacing AI with numerical simulation.
Home-page: https://github.com/mimesis-inria/DeepPhysX
Author: Mimesis
Author-email: robin.enjalbert@inria.fr
License-File: LICENSE
Requires-Dist: SimulationSimpleDatabase (>=22.12)
Requires-Dist: numpy (>=1.23.5)
Requires-Dist: tensorboard (>=2.10.0)
Requires-Dist: tensorboardX (>=2.5.1)
Requires-Dist: pyDataverse (>=0.3.1)
Requires-Dist: torch (>=1.13.0)
